pyfree/FreeAPI.py
pyfree/__init__.py
pyfree/__main__.py
pyfree/config.txt
pyfree-1.0.0.dist-info/LICENSE
pyfree-1.0.0.dist-info/METADATA
pyfree-1.0.0.dist-info/WHEEL
pyfree-1.0.0.dist-info/entry_points.txt
pyfree-1.0.0.dist-info/top_level.txt
pyfree-1.0.0.dist-info/RECORD
