Metadata-Version: 2.1
Name: pyfree
Version: 1.0.0
Summary: A lib for free APIs
Home-page: https://github.com/rayvikram/pyfree
Author: Vikram Ray
Author-email: vik8876@gmail.com
License: UNKNOWN
Platform: UNKNOWN
Classifier: Programming Language :: Python :: 3
Classifier: License :: OSI Approved :: MIT License
Classifier: Operating System :: OS Independent
Requires-Python: >=3.6
Requires-Dist: requests
